setup.py
src/textminer/__init__.py
src/textminer/errors.py
src/textminer/extractors.py
src/textminer/filters.py
src/textminer/main.py
src/textminer/matchers.py
src/textminer/util.py
src/textminer.egg-info/PKG-INFO
src/textminer.egg-info/SOURCES.txt
src/textminer.egg-info/dependency_links.txt
src/textminer.egg-info/requires.txt
src/textminer.egg-info/top_level.txt