Metadata-Version: 1.1
Name: textminer
Version: 1.3.1
Summary: Extracts content from html using rules.
Home-page: https://github.com/cooledcoffee/textminer
Author: Mengchen LEE
Author-email: UNKNOWN
License: UNKNOWN
Platform: UNKNOWN
Classifier: Development Status :: 4 - Beta
Classifier: Intended Audience :: Developers
Classifier: Operating System :: OS Independent
Classifier: Programming Language :: Python
Classifier: Programming Language :: Python :: 2
Classifier: Programming Language :: Python :: 3
Classifier: Topic :: Software Development :: Libraries
Classifier: Topic :: Internet
Classifier: Topic :: Text Processing :: Markup :: HTML
